{"type":"FeatureCollection","features":[{"type":"Feature","properties":{"numberAnke":"160","numberOfficial":"209","name":"Handschwengelpumpe","district":"Altlindenau","address":"Karl-Ferlemann-Straße","date":null,"description":"Handschwengelpumpe mit Brunnenschacht und Abdeckplatte in Ecklage Geraer Straße","type":"unbekannt","stateDescription":"wahrscheinlich abgebaut","physicalState":"nicht vorhanden","detailedPhysicalState":"nicht weiter spezifiert","operatingState":"außer Betrieb","feedingDescription":null,"lastFeeding":null,"controlsDescription":null,"lastControl":null},"geometry":{"type":"Point","coordinates":[12.3242,51.336887]},"id":"160"},{"type":"Feature","properties":{"numberAnke":"152","numberOfficial":"241","name":"Handschwengelpumpe","district":"Altlindenau","address":"William-Zipperer-Straße","date":null,"description":"Handschwengelpumpe mit Brunnenschacht und Abdeckplatte in Ecklage Calvisiusstraße (Typ Vogelkäfig)","type":"Vogelkäfig","stateDescription":"wahrscheinlich abgebaut","physicalState":"nicht vorhanden","detailedPhysicalState":"nicht weiter spezifiert","operatingState":"außer Betrieb","feedingDescription":null,"lastFeeding":null,"controlsDescription":null,"lastControl":null},"geometry":{"type":"Point","coordinates":[12.329865,51.33839]},"id":"152"}]}