{"type":"FeatureCollection","features":[{"type":"Feature","properties":{"numberAnke":"15","numberOfficial":"150","name":"Handschwengelpumpe [Torso]","district":"Anger-Crottendorf","address":"Bernhardstraße","date":null,"description":"Torso einer Handschwengelpumpe mit Brunnenschacht und Abdeckplatte vor Nr. 7 (Typ Delphin)","state":"wahrscheinlich nur alter Torso vorhanden","feeding":null,"controls":null},"geometry":{"type":"Point","coordinates":[12.40911,51.33839]},"id":"15"},{"type":"Feature","properties":{"numberAnke":"19","numberOfficial":"151","name":"Handschwengelpumpe","district":"Anger-Crottendorf","address":"Borsdorfer Straße","date":null,"description":"Handschwengelpumpe mit Brunnenschacht und Abdeckplatte (Typ Gotik) sowie Kleinpflaster und Granitschwellen der kleinen Verkehrsinsel in Ecklage Theodor-Neubauer-Straße","state":"abgebaut [Anke] --> wäre schöner Standort","feeding":null,"controls":null},"geometry":{"type":"Point","coordinates":[12.41111,51.3353]},"id":"19"},{"type":"Feature","properties":{"numberAnke":"112","numberOfficial":null,"name":"Drei Handschwengelpumpen","district":"Anger-Crottendorf","address":"Oststraße 119","date":null,"description":"Drei Handschwengelpumpen mit Brunnenschacht und Abdeckplatte auf dem Ostfriedhof, 3. Abteilung und vor der Kapelle Oststraße Nr. 119","state":null,"feeding":null,"controls":null},"geometry":{"type":"Point","coordinates":[12.418274,51.32845]},"id":"112"},{"type":"Feature","properties":{"numberAnke":"151","numberOfficial":"186","name":"Handschwengelpumpe","district":"Anger-Crottendorf","address":"Wichernstraße","date":null,"description":"Handschwengelpumpe mit Brunnenschacht und Abdeckplatte neben Nr. 2 in Ecklage Zweinaundorfer Straße (Typ Delphin)","state":"wahrscheinlich abgebaut","feeding":null,"controls":null},"geometry":{"type":"Point","coordinates":[12.41971,51.33327]},"id":"151"}]}