{"type":"FeatureCollection","features":[{"type":"Feature","properties":{"numberAnke":"40","numberOfficial":"250","name":"Handschwengelpumpe","district":"Gohlis-Süd","address":"Ehrensteinstraße","date":null,"description":"Handschwengelpumpe mit Brunnenschacht und Abdeckplatte Ecke Gohliser Straße","state":"wahrscheinlich abgebaut","feeding":null,"controls":null},"geometry":{"type":"Point","coordinates":[null,null]},"id":"40"},{"type":"Feature","properties":{"numberAnke":"47","numberOfficial":"234","name":"Handschwengelpumpe","district":"Gohlis-Süd","address":"Fritz-Seger-Straße","date":null,"description":"Handschwengelpumpe mit Brunnenschacht und Abdeckplatte (Typ Vogelkäfig)","state":"wahrscheinlich nur alter Torso vorhanden","feeding":null,"controls":null},"geometry":{"type":"Point","coordinates":[12.37124,51.3586]},"id":"47"},{"type":"Feature","properties":{"numberAnke":"61","numberOfficial":"260","name":"Handschwengelpumpe [abgebaut]","district":"Gohlis-Süd","address":"Herloßsohnstraße","date":null,"description":"Handschwengelpumpe mit Brunnenschacht und Abdeckplatte in Ecklage Möckernsche Straße gegenüber Herloßsohnstraße 2","state":"wahrscheinlich abgebaut","feeding":null,"controls":null},"geometry":{"type":"Point","coordinates":[12.3571,51.36157]},"id":"61"},{"type":"Feature","properties":{"numberAnke":"78","numberOfficial":"132","name":"Handschwengelpumpe","district":"Gohlis-Süd","address":"Kirchplatz","date":null,"description":"Handschwengelpumpe mit Brunnenschacht und Abdeckplatte (Typ Gotik) Kirchplatz Gohlis, an der Lützowstraße","state":"wahrscheinlich nur noch Stumpf vorhanden","feeding":null,"controls":null},"geometry":{"type":"Point","coordinates":[null,null]},"id":"78"},{"type":"Feature","properties":{"numberAnke":"85","numberOfficial":"265","name":"Handschwengelpumpe","district":"Gohlis-Süd","address":"Lindenthaler Straße","date":null,"description":"Handschwengelpumpe mit Brunnenschacht und Abdeckplatte in Ecklage Berggartenstraße vor Nr. 1 (Typ Delphin)","state":"wahrscheinlich nur verosteter<Fragezeichen> Torso vorhanden","feeding":null,"controls":null},"geometry":{"type":"Point","coordinates":[12.36543,51.35934]},"id":"85"},{"type":"Feature","properties":{"numberAnke":"133","numberOfficial":"197","name":"Handschwengelpumpe","district":"Gohlis-Süd","address":"Schachtstraße","date":null,"description":"Handschwengelpumpe mit Brunnenschacht und Abdeckplatte in Ecklage Georg-Schumann-Straße (Typ Delphin)","state":"wahrscheinlich nur verosteter<Fragezeichen> Torso vorhanden","feeding":null,"controls":null},"geometry":{"type":"Point","coordinates":[12.36019,51.3638]},"id":"133"}]}