{"type":"FeatureCollection","features":[{"type":"Feature","properties":{"numberAnke":"56","numberOfficial":"115","name":"Handschwengelpumpe [Torso]","district":"Zentrum-Süd","address":"Härtelstraße","date":"um 1880 (Handschwengelpumpe)","description":"Handschwengelpumpe mit Brunnenschacht und Abdeckplatte vor Nr. 11 (Typ Gotik)","state":"wahrscheinlich nur alter Torso vorhanden","feeding":null,"controls":null},"geometry":{"type":"Point","coordinates":[12.37609,51.33273]},"id":"56"},{"type":"Feature","properties":{"numberAnke":"161","numberOfficial":"178","name":"Handschwengelpumpe","district":"Zentrum-Süd","address":"Karl-Liebknecht-Straße 44","date":null,"description":"Handschwengelpumpe mit Brunnenschacht und Abdeckplatte","state":"abgebaut [Anke]","feeding":null,"controls":null},"geometry":{"type":"Point","coordinates":[null,null]},"id":"161"},{"type":"Feature","properties":{"numberAnke":"99","numberOfficial":"93","name":"Handschwengelpumpe","district":"Zentrum-Süd","address":"Markthallenstraße","date":null,"description":"Handschwengelpumpe mit Brunnenschacht und Fassung","state":"Standort nicht gefunden, wahrscheinlich gar nicht mehr vorhanden (jetzt Eingang S-Bahn-Station) [Anke]","feeding":null,"controls":null},"geometry":{"type":"Point","coordinates":[null,null]},"id":"99"},{"type":"Feature","properties":{"numberAnke":"113","numberOfficial":"176","name":"Handschwengelpumpe [abgebaut]","district":"Zentrum-Süd","address":"Paul-Gruner-Straße","date":null,"description":"Handschwengelpumpe mit Brunnenschacht und Abdeckplatte in Ecklage Arthur-Hoffmann-Straße","state":"abgebaut [Anke]","feeding":null,"controls":null},"geometry":{"type":"Point","coordinates":[12.37985,51.32764]},"id":"113"},{"type":"Feature","properties":{"numberAnke":"114","numberOfficial":"191","name":"Handschwengelpumpe","district":"Zentrum-Süd","address":"Paul-Gruner-Straße","date":null,"description":"Handschwengelpumpe mit Brunnenschacht und Abdeckplatte (am Floßplatz)","state":"Standort wahrscheinlich nicht mehr vorhanden","feeding":null,"controls":null},"geometry":{"type":"Point","coordinates":[null,null]},"id":"114"},{"type":"Feature","properties":{"numberAnke":"115","numberOfficial":"1","name":"Handschwengelpumpe [rekonstruiert]","district":"Zentrum-Süd","address":"Peterssteinweg 10","date":"nach 1910 (Handschwengelpumpe)","description":"Handschwengelpumpe mit Brunnenschacht und Abdeckplatte in Ecklage Münzgasse (Typ Vogelkäfig)","state":"betriebsbereit","feeding":null,"controls":null},"geometry":{"type":"Point","coordinates":[12.37349,51.33278]},"id":"115"},{"type":"Feature","properties":{"numberAnke":"125","numberOfficial":"123","name":"Handschwengelpumpe","district":"Zentrum-Süd","address":"Riemannstraße 54","date":"um 1910 (Handschwengelpumpe)","description":"Handschwengelpumpe mit Brunnenschacht in Ecklage Harkortstraße, gegenüber Riemannstraße 54 (Typ Kleiner Löwe)","state":"wahrscheinlich abgebaut","feeding":null,"controls":null},"geometry":{"type":"Point","coordinates":[null,null]},"id":"125"}]}